badger_mk/__init__.py
badger_mk/__main__.py
badger_mk-0.1.4.dist-info/LICENSE
badger_mk-0.1.4.dist-info/METADATA
badger_mk-0.1.4.dist-info/WHEEL
badger_mk-0.1.4.dist-info/entry_points.txt
badger_mk-0.1.4.dist-info/top_level.txt
badger_mk-0.1.4.dist-info/RECORD
