Metadata-Version: 2.1
Name: badger-mk
Version: 0.1.4
Summary: Makes badges from templates
Home-page: https://github.com/lcnittl/badger-mk
Author: Christian Knittl-Frank
Author-email: lcnittl@gmail.com
License: GPL-3.0
Download-URL: http://pypi.python.org/pypi/badger-mk
Project-URL: GitHub: repo, https://github.com/lcnittl/badger-mk
Project-URL: GitHub: issues, https://github.com/lcnittl/badger-mk/issues
Platform: UNKNOWN
Classifier: Development Status :: 3 - Alpha
Classifier: Environment :: Console
Classifier: Intended Audience :: End Users/Desktop
Classifier: License :: OSI Approved :: GNU General Public License v3 (GPLv3)
Classifier: License :: OSI Approved :: GNU General Public License v3 or later (GPLv3+)
Classifier: Operating System :: OS Independent
Classifier: Programming Language :: Python :: 3
Classifier: Programming Language :: Python :: 3 :: Only
Classifier: Programming Language :: Python :: 3.8
Classifier: Programming Language :: Python :: 3.9
Classifier: Topic :: Artistic Software
Classifier: Topic :: Multimedia :: Graphics
Classifier: Topic :: Utilities
Requires-Python: >=3.8
License-File: LICENSE
Requires-Dist: CairoSVG (>=2.5.0)
Requires-Dist: GitPython (>=3.1.11)
Requires-Dist: PyPDF2 (>=1.26.0)
Requires-Dist: colorlog (>=4.6.2)
Requires-Dist: lxml (>=4.6.1)
